<values>
<value name="filament1"
type="string"/>
<value name="fillPattern"
type="string">honeycomb</value>
<value name="topFillPattern"
type="string">rectilinear</value>
<value name="filament15"
type="string"/>
<value name="filament4"
type="string"/>
<value name="supportMaterial"
type="int">0</value>
<value name="ironing"
type="int">0</value>
<value name="fillAngle"
type="string">45</value>
<value name="filament3"
type="string"/>
<value name="filament8"
type="string"/>
<value name="filament5"
type="string"/>
<value name="print"
type="string"/>
<value name="filament2"
type="string"/>
<value name="printer"
type="string"/>
<value name="filament9"
type="string"/>
<value name="fillDensity"
type="string">0.2</value>
<value name="solidFillPatern"
type="string">rectilinear</value>
<value name="filament6"
type="string"/>
<value name="filament14"
type="string"/>
<value name="filament11"
type="string"/>
<value name="version"
type="int">1</value>
<value name="bottomFillPattern"
type="string">rectilinear</value>
<value name="filament12"
type="string"/>
<value name="filament13"
type="string"/>
<value name="overrideSettings"
type="int">0</value>
<value name="preservePositions"
type="int">0</value>
<value name="cooling"
type="int">1</value>
<value name="layerHeight"
type="string">0.2</value>
<value name="filament10"
type="string"/>
<value name="filament16"
type="string"/>
<value name="filament7"
type="string"/>
<value name="wipeLoadUnloadVolume"
type="string">70</value>
</values>
